{"cameraMode":{"drawMode":0,"name":"Shaded","section":"Shading Mode"},"sceneLighting":true,"audioPlay":false,"sceneViewState":{"m_AlwaysRefresh":false,"showFog":true,"showSkybox":true,"showFlares":true,"showImageEffects":true,"showParticleSystems":true,"showVisualEffectGraphs":true,"m_FxEnabled":true},"in2DMode":false,"pivot":{"x":-0.027748718857765199,"y":-11.543521881103516,"z":3.9319069385528566},"rotation":{"x":0.6472180485725403,"y":0.026300059631466867,"z":-0.02232152409851551,"w":0.7615793347358704},"size":31.64613914489746,"orthographic":false}